qvd_utils-0.1.15.dist-info/METADATA
qvd_utils-0.1.15.dist-info/WHEEL
qvd_utils/test_files/test_qvd_null.qvd
qvd_utils/test_files/AAPL.qvd
qvd_utils/test_files/test_qvd.qvd
qvd_utils/test_files/AAPL.csv
qvd_utils/qvd_reader.py
qvd_utils/test_qvd_reader.py
qvd_utils/test_qvd_reader_chunk.py
qvd_utils/__init__.py
qvd_utils/qvd_utils.cpython-310-x86_64-linux-gnu.so
qvd_utils-0.1.15.dist-info/RECORD
