Metadata-Version: 2.1
Name: qvd_utils
Version: 0.1.15
Summary: A library for reading Qlik Sense .qvd file format from Python, written in Rust.
Keywords: python,rust,qlik,sense,qvd
Author: Hugo Tallys <hgtllys@gmail.com>
Author-email: Hugo Tallys <hgtllys@gmail.com>
License: Apache-2.0
Project-URL: Source Code, https://github.com/hugotallys/qvd-utils
